[
  {
    "Дата": "21-03-2022",
    "ФИО": "Первый пациент",
    "Диагноз": "Хронический геморрой 1 ст.",
    "Рекомендации": "Свечи с облепиховым маслом 2 р в день"
  },
  {
    "Дата": "22-03-2022",
    "ФИО": "Второй пациент",
    "Диагноз": "Хронический геморрой 2 ст.",
    "Рекомендации": "Свечи с облепиховым маслом 2 р в день"
  },
  {
    "Дата": "23-03-2022",
    "ФИО": "третий пациент",
    "Диагноз": "Хронический геморрой 3 ст.",
    "Рекомендации": "Свечи с облепиховым маслом 2 р в день"
  }
]
